README.md
setup.py
csshy/__init__.py
csshy/__main__.py
csshy/backends.py
csshy/cssh.py
csshy/csshy.py
csshy/migrate_settings_from_csshnator.py
csshy/terminator.py
csshy/tilix.py
csshy/utils.py
csshy.egg-info/PKG-INFO
csshy.egg-info/SOURCES.txt
csshy.egg-info/dependency_links.txt
csshy.egg-info/entry_points.txt
csshy.egg-info/not-zip-safe
csshy.egg-info/requires.txt
csshy.egg-info/top_level.txt