Metadata-Version: 1.1
Name: csshy
Version: 0.1
Summary: Improved ClusterSSH for modern terminals like Terminator and Tilix
Home-page: https://github.com/thor27/csshy
Author: Thomaz Reis
Author-email: thor27@gmail.com
License: GPLv3
Keywords: funniest joke comedy flying circus
Platform: UNKNOWN
Classifier: Development Status :: 3 - Alpha
Classifier: License :: OSI Approved :: GNU General Public License v3 (GPLv3)
Classifier: Environment :: Console
Classifier: Operating System :: POSIX :: Linux
